cdk/codepipeline_extensions/__init__.py
cdk/codepipeline_extensions/py.typed
cdk/codepipeline_extensions/_jsii/__init__.py
cdk/codepipeline_extensions/_jsii/cdk-codepipeline-extensions@0.1.0.jsii.tgz
cdklabs.codepipeline_extensions-0.1.0.dist-info/LICENSE
cdklabs.codepipeline_extensions-0.1.0.dist-info/METADATA
cdklabs.codepipeline_extensions-0.1.0.dist-info/NOTICE
cdklabs.codepipeline_extensions-0.1.0.dist-info/WHEEL
cdklabs.codepipeline_extensions-0.1.0.dist-info/top_level.txt
cdklabs.codepipeline_extensions-0.1.0.dist-info/RECORD
